wxy121517761848/__init__.py
wxy121517761848/fusion.py
wxy121517761848-0.0.12.dist-info/LICENSE
wxy121517761848-0.0.12.dist-info/WHEEL
wxy121517761848-0.0.12.dist-info/METADATA
wxy121517761848-0.0.12.dist-info/RECORD
