Metadata-Version: 2.1
Name: wxy121517761848
Version: 0.0.12
Summary: Some lite description.
Home-page: https://github.com/nazq/wxy121517761848
License: Apache-2.0
Author: Anon
Author-email: naz.quadri@gmail.com
Requires-Python: >=3.7.1,<4.0
Classifier: Development Status :: 2 - Pre-Alpha
Classifier: Intended Audience :: Developers
Classifier: License :: OSI Approved :: Apache Software License
Classifier: Natural Language :: English
Classifier: Programming Language :: Python :: 3
Classifier: Programming Language :: Python :: 3.10
Classifier: Programming Language :: Python :: 3.7
Classifier: Programming Language :: Python :: 3.8
Classifier: Programming Language :: Python :: 3.9
Provides-Extra: dev
Provides-Extra: doc
Provides-Extra: test
Requires-Dist: black (>=22.3.0,<23.0.0); extra == "test"
Requires-Dist: bump2version (>=1.0.1,<2.0.0); extra == "dev"
Requires-Dist: flake8 (>=3.9.2,<4.0.0); extra == "test"
Requires-Dist: flake8-docstrings (>=1.6.0,<2.0.0); extra == "test"
Requires-Dist: isort (>=5.8.0,<6.0.0); extra == "test"
Requires-Dist: jinja2 (>=2.11.3,<3.0.0)
Requires-Dist: joblib (>=1.1.0,<2.0.0)
Requires-Dist: markupsafe (==2.0.1)
Requires-Dist: mike (>=1.1.2,<2.0.0); extra == "doc"
Requires-Dist: mkdocs (>=1.2.3,<2.0.0); extra == "doc"
Requires-Dist: mkdocs-autorefs (>=0.2.1,<0.3.0); extra == "doc"
Requires-Dist: mkdocs-git-revision-date-plugin (>=0.3.1,<0.4.0); extra == "doc"
Requires-Dist: mkdocs-include-markdown-plugin (>=2.8.0,<3.0.0); extra == "doc"
Requires-Dist: mkdocs-material (>=8.1.0,<9.0.0); extra == "doc"
Requires-Dist: mkdocs-material-extensions (>=1.0.1,<2.0.0)
Requires-Dist: mkdocstrings (>=0.16.0,<0.17.0); extra == "doc"
Requires-Dist: mypy (>=0.900,<0.901); extra == "test"
Requires-Dist: pandas (>1.1.1)
Requires-Dist: pip (>=20.3.1,<21.0.0); extra == "dev"
Requires-Dist: pre-commit (>=2.12.0,<3.0.0); extra == "dev"
Requires-Dist: pytest (>=6.2.4,<7.0.0); extra == "test" or extra == "dev"
Requires-Dist: pytest-cov (>=2.12.0,<3.0.0); extra == "test" or extra == "dev"
Requires-Dist: requests (>2.27.0)
Requires-Dist: tabulate (>=0.8.9,<0.9.0)
Requires-Dist: toml (>=0.10.2,<0.11.0); extra == "dev"
Requires-Dist: tox (>=3.20.1,<4.0.0); extra == "dev"
Requires-Dist: tox-conda (>=0.8.2,<0.9.0); extra == "dev"
Requires-Dist: tqdm (>=4.64.0,<5.0.0)
Requires-Dist: twine (>=3.3.0,<4.0.0); extra == "dev"
Requires-Dist: types-requests (>2.27.0)
Requires-Dist: types-tabulate (>=0.8.8,<0.9.0)
Requires-Dist: virtualenv (>=20.2.2,<21.0.0); extra == "dev"
